<annotation>
	<folder>PNGImages</folder>
	<filename>PennPed00004.png</filename>
	<path>C:\Users\q0920\Desktop\PennFudanPed\PNGImages\PennPed00004.png</path>
	<source>
		<database>Unknown</database>
	</source>
	<size>
		<width>786</width>
		<height>436</height>
		<depth>3</depth>
	</size>
	<segmented>0</segmented>
	<object>
		<name>people</name>
		<pose>Unspecified</pose>
		<truncated>0</truncated>
		<difficult>0</difficult>
		<bndbox>
			<xmin>405</xmin>
			<ymin>96</ymin>
			<xmax>515</xmax>
			<ymax>391</ymax>
		</bndbox>
	</object>
	<object>
		<name>people</name>
		<pose>Unspecified</pose>
		<truncated>0</truncated>
		<difficult>0</difficult>
		<bndbox>
			<xmin>575</xmin>
			<ymin>99</ymin>
			<xmax>739</xmax>
			<ymax>393</ymax>
		</bndbox>
	</object>
	<object>
		<name>people</name>
		<pose>Unspecified</pose>
		<truncated>0</truncated>
		<difficult>0</difficult>
		<bndbox>
			<xmin>221</xmin>
			<ymin>93</ymin>
			<xmax>329</xmax>
			<ymax>401</ymax>
		</bndbox>
	</object>
	<object>
		<name>people</name>
		<pose>Unspecified</pose>
		<truncated>0</truncated>
		<difficult>0</difficult>
		<bndbox>
			<xmin>150</xmin>
			<ymin>89</ymin>
			<xmax>248</xmax>
			<ymax>381</ymax>
		</bndbox>
	</object>
	<object>
		<name>people</name>
		<pose>Unspecified</pose>
		<truncated>0</truncated>
		<difficult>0</difficult>
		<bndbox>
			<xmin>73</xmin>
			<ymin>55</ymin>
			<xmax>178</xmax>
			<ymax>429</ymax>
		</bndbox>
	</object>
</annotation>
